{"version":1,"resource":"file:///home/shawaiz/Root%20Data/Personal%20Brand/Projects/App%20Dev%20projects/todo_app/lib/data/models/user_model.dart","entries":[{"id":"oC66.dart","timestamp":1767692789175},{"id":"QRzn.dart","source":"undoRedo.source","timestamp":1767692795119},{"id":"DjJY.dart","timestamp":1767692800228},{"id":"m20R.dart","timestamp":1767692810721},{"id":"6SEI.dart","timestamp":1767692824629},{"id":"6DXB.dart","timestamp":1767693291415},{"id":"7PQG.dart","timestamp":1767693358085},{"id":"NNKN.dart","timestamp":1767696925303},{"id":"FLjb.dart","timestamp":1767696945387},{"id":"n3ca.dart","timestamp":1767696963718},{"id":"HbpW.dart","timestamp":1767696976904},{"id":"HVED.dart","timestamp":1767697003517},{"id":"FreO.dart","timestamp":1767697024728},{"id":"2BO1.dart","timestamp":1767697060573},{"id":"HalF.dart","timestamp":1767697080750},{"id":"BieH.dart","timestamp":1767697095620},{"id":"cYaH.dart","source":"undoRedo.source","timestamp":1767697131725},{"id":"KnMj.dart","timestamp":1767697329387},{"id":"Hr65.dart","timestamp":1767698289551},{"id":"OU8F.dart","timestamp":1767805255900},{"id":"Pci3.dart","timestamp":1767805270271},{"id":"GLHJ.dart","timestamp":1767805291152},{"id":"XJKF.dart","timestamp":1767805309028},{"id":"SyQt.dart","source":"undoRedo.source","timestamp":1767805324457},{"id":"GyOs.dart","timestamp":1767805335703},{"id":"4GrO.dart","timestamp":1767805347917},{"id":"e1Fw.dart","timestamp":1767805375649},{"id":"6vvQ.dart","source":"undoRedo.source","timestamp":1767805471678},{"id":"wPls.dart","timestamp":1767805714657},{"id":"W2zs.dart","timestamp":1767805807916},{"id":"rKns.dart","timestamp":1767805845477},{"id":"imlQ.dart","timestamp":1767805863004},{"id":"Np5J.dart","timestamp":1767805874364}]}