{"version":1,"resource":"file:///home/shawaiz/Root%20Data/Personal%20Brand/Projects/POW%20It%20Up%20Projects/keycloak-test/nextjs/Dockerfile","entries":[{"id":"r3iZ","timestamp":1767959201769},{"id":"1CcR","source":"undoRedo.source","timestamp":1767959202451},{"id":"8D0a","timestamp":1767959268098},{"id":"qniZ","timestamp":1767972092844},{"id":"OoSZ","timestamp":1767972159562},{"id":"ttWK","timestamp":1767972894471},{"id":"shgK","timestamp":1767973726142},{"id":"8a8T","source":"moved.source","sourceDescription":"~/Root Data/Personal Brand/Projects/POW It Up Projects/keycloak-test/Dockerfile","timestamp":1767974416529},{"id":"7Imh","timestamp":1767986316738},{"id":"AaAX","timestamp":1768246971970}]}