{"version":1,"resource":"file:///home/shawaiz/Root%20Data/Personal%20Brand/Projects/App%20Dev%20projects/after-me-private-offline-diary/app/%28tabs%29/_layout.tsx","entries":[{"id":"6jHR.tsx","timestamp":1766746510044},{"id":"O1c6.tsx","timestamp":1766746538009},{"id":"Dmuv.tsx","source":"undoRedo.source","timestamp":1766746542073},{"id":"9Tsg.tsx","timestamp":1766746576977},{"id":"buE8.tsx","timestamp":1766746599626},{"id":"lBTw.tsx","timestamp":1766746640848},{"id":"nxXA.tsx","timestamp":1766748117308}]}